romi/__init__.py
romi/py.typed
romi/version.py
romi/src/main.cpp
romi/_init__romi.py
romi/_romi.cpython-310-x86_64-linux-gnu.so
romi/_romi.pyi
romi/romi.pc
romi/trampolines/frc__OnBoardIO.hpp
romi/trampolines/frc__RomiGyro.hpp
romi/trampolines/frc__RomiMotor.hpp
robotpy_romi-2025.3.2.3.dist-info/METADATA
robotpy_romi-2025.3.2.3.dist-info/WHEEL
robotpy_romi-2025.3.2.3.dist-info/entry_points.txt
robotpy_romi-2025.3.2.3.dist-info/RECORD
