Metadata-Version: 2.4
Name: robotpy-romi
Version: 2025.3.2.3
Summary: Binary wrapper for WPILib Romi Vendor library
Project-URL: Source code, https://github.com/robotpy/mostrobotpy
Author-email: RobotPy Development Team <robotpy@googlegroups.com>
License-Expression: BSD-3-Clause
Requires-Dist: robotpy-native-romi==2025.3.2
Requires-Dist: wpilib==2025.3.2.3
